ctkmessagebox2/__init__.py
ctkmessagebox2/ctkmessagebox.py
ctkmessagebox2/demo.py
ctkmessagebox2/icons/alert-icon.png
ctkmessagebox2/icons/ask-icon.png
ctkmessagebox2/icons/error-icon.png
ctkmessagebox2/icons/info-icon.png
ctkmessagebox2/icons/ok-icon.png
ctkmessagebox2-0.3.4.dist-info/licenses/LICENSE
ctkmessagebox2-0.3.4.dist-info/METADATA
ctkmessagebox2-0.3.4.dist-info/WHEEL
ctkmessagebox2-0.3.4.dist-info/top_level.txt
ctkmessagebox2-0.3.4.dist-info/RECORD
