Metadata-Version: 2.4
Name: ctkmessagebox2
Version: 0.3.4
Summary: The messagebox package for CustomTkinter.
Home-page: https://github.com/hoffmanlucas/ctkmessagebox.git
Author: Lucas Hoffman
Author-email: Lucas Hoffman <hoffmanlucas@gmail.com>
Project-URL: Homepage, https://github.com/hoffmanlucas/ctkmessagebox
Project-URL: Issues, https://github.com/hoffmanlucas/ctkmessagebox/issues
Classifier: Programming Language :: Python :: 3
Classifier: License :: OSI Approved :: MIT License
Classifier: Operating System :: OS Independent
Requires-Python: >=3.6
License-File: LICENSE
Dynamic: author
Dynamic: home-page
Dynamic: license-file
Dynamic: requires-python
